{"items":[{"owner":{"account_id":112317,"reputation":91807,"user_id":296328,"user_type":"registered","accept_rate":60,"profile_image":"https://i.stack.imgur.com/DSpH6.jpg?s=256&g=1","display_name":"khmarbaise","link":"https://stackoverflow.com/users/296328/khmarbaise"},"edited":false,"score":0,"creation_date":1684174376,"post_id":76255226,"comment_id":134475697,"content_license":"CC BY-SA 4.0"},{"owner":{"account_id":19092422,"reputation":48221,"user_id":13942448,"user_type":"registered","profile_image":"https://i.stack.imgur.com/yzJsY.jpg?s=256&g=1","display_name":"jccampanero","link":"https://stackoverflow.com/users/13942448/jccampanero"},"edited":false,"score":0,"creation_date":1684171504,"post_id":76178871,"comment_id":134475094,"content_license":"CC BY-SA 4.0"},{"owner":{"account_id":8773814,"reputation":265,"user_id":6559689,"user_type":"registered","profile_image":"https://graph.facebook.com/597915423703256/picture?type=large","display_name":"colorgreen","link":"https://stackoverflow.com/users/6559689/colorgreen"},"reply_to_user":{"account_id":112317,"reputation":91807,"user_id":296328,"user_type":"registered","accept_rate":60,"profile_image":"https://i.stack.imgur.com/DSpH6.jpg?s=256&g=1","display_name":"khmarbaise","link":"https://stackoverflow.com/users/296328/khmarbaise"},"edited":false,"score":0,"creation_date":1684167243,"post_id":76255226,"comment_id":134474139,"content_license":"CC BY-SA 4.0"},{"owner":{"account_id":93689,"reputation":408527,"user_id":256196,"user_type":"moderator","accept_rate":77,"profile_image":"https://www.gravatar.com/avatar/d84b558fd67be10d5a718fb94231909d?s=256&d=identicon&r=PG","display_name":"Bohemian","link":"https://stackoverflow.com/users/256196/bohemian"},"edited":false,"score":0,"creation_date":1684165940,"post_id":76255269,"comment_id":134473791,"content_license":"CC BY-SA 4.0"},{"owner":{"account_id":112317,"reputation":91807,"user_id":296328,"user_type":"registered","accept_rate":60,"profile_image":"https://i.stack.imgur.com/DSpH6.jpg?s=256&g=1","display_name":"khmarbaise","link":"https://stackoverflow.com/users/296328/khmarbaise"},"edited":false,"score":0,"creation_date":1684164774,"post_id":76255226,"comment_id":134473485,"content_license":"CC BY-SA 4.0"},{"owner":{"account_id":8057140,"reputation":3011,"user_id":6073886,"user_type":"registered","profile_image":"https://www.gravatar.com/avatar/ed821e335bc77250d384db114db82d17?s=256&d=identicon&r=PG&f=y&so-version=2","display_name":"OH GOD SPIDERS","link":"https://stackoverflow.com/users/6073886/oh-god-spiders"},"edited":false,"score":0,"creation_date":1684162347,"post_id":76255269,"comment_id":134472798,"content_license":"CC BY-SA 4.0"},{"owner":{"account_id":213468,"reputation":98961,"user_id":466862,"user_type":"registered","profile_image":"https://www.gravatar.com/avatar/d873f397779db38cd510d9ee5416fd43?s=256&d=identicon&r=PG","display_name":"Mark Rotteveel","link":"https://stackoverflow.com/users/466862/mark-rotteveel"},"edited":false,"score":0,"creation_date":1684162289,"post_id":76255269,"comment_id":134472776,"content_license":"CC BY-SA 4.0"},{"owner":{"account_id":21821517,"reputation":13,"user_id":16253011,"user_type":"registered","profile_image":"https://lh3.googleusercontent.com/a/AATXAJy9CPG9i3UNHKN9YY1dGWPrhHvzoZiPmHWvy0qU=k-s256","display_name":"trying  to be developer","link":"https://stackoverflow.com/users/16253011/trying-to-be-developer"},"edited":false,"score":0,"creation_date":1684157966,"post_id":76254367,"comment_id":134471664,"content_license":"CC BY-SA 4.0"},{"owner":{"account_id":1449141,"reputation":37413,"user_id":1447509,"user_type":"registered","accept_rate":89,"profile_image":"https://i.stack.imgur.com/AYREu.jpg?s=256&g=1","display_name":"cssyphus","link":"https://stackoverflow.com/users/1447509/cssyphus"},"edited":false,"score":0,"creation_date":1684157683,"post_id":76254367,"comment_id":134471601,"content_license":"CC BY-SA 4.0"},{"owner":{"account_id":21821517,"reputation":13,"user_id":16253011,"user_type":"registered","profile_image":"https://lh3.googleusercontent.com/a/AATXAJy9CPG9i3UNHKN9YY1dGWPrhHvzoZiPmHWvy0qU=k-s256","display_name":"trying  to be developer","link":"https://stackoverflow.com/users/16253011/trying-to-be-developer"},"edited":false,"score":0,"creation_date":1684157511,"post_id":76254367,"comment_id":134471564,"content_license":"CC BY-SA 4.0"},{"owner":{"account_id":10162,"reputation":904312,"user_id":19068,"user_type":"registered","profile_image":"https://www.gravatar.com/avatar/1d2d3229ed1961d2bd81853242493247?s=256&d=identicon&r=PG","display_name":"Quentin","link":"https://stackoverflow.com/users/19068/quentin"},"edited":false,"score":0,"creation_date":1684156794,"post_id":76254367,"comment_id":134471382,"content_license":"CC BY-SA 4.0"},{"owner":{"account_id":29476,"reputation":27227,"user_id":79677,"user_type":"registered","accept_rate":68,"profile_image":"https://www.gravatar.com/avatar/a7406333f1543ae134008d738c53066f?s=256&d=identicon&r=PG&f=y&so-version=2","display_name":"FiniteLooper","link":"https://stackoverflow.com/users/79677/finitelooper"},"edited":false,"score":0,"creation_date":1684156647,"post_id":76254367,"comment_id":134471347,"content_license":"CC BY-SA 4.0"},{"owner":{"account_id":129540,"reputation":204498,"user_id":328193,"user_type":"registered","accept_rate":91,"profile_image":"https://i.stack.imgur.com/FnwU5.jpg?s=256&g=1","display_name":"David","link":"https://stackoverflow.com/users/328193/david"},"edited":false,"score":2,"creation_date":1684156423,"post_id":76254367,"comment_id":134471303,"content_license":"CC BY-SA 4.0"},{"owner":{"account_id":26408874,"reputation":190,"user_id":20058203,"user_type":"registered","profile_image":"https://i.stack.imgur.com/9UCUN.jpg?s=256&g=1","display_name":"AJ Zack","link":"https://stackoverflow.com/users/20058203/aj-zack"},"edited":false,"score":0,"creation_date":1684155927,"post_id":76254367,"comment_id":134471186,"content_license":"CC BY-SA 4.0"},{"owner":{"account_id":372682,"reputation":19665,"user_id":721855,"user_type":"registered","profile_image":"https://i.stack.imgur.com/vZiox.png?s=256&g=1","display_name":"aled","link":"https://stackoverflow.com/users/721855/aled"},"edited":false,"score":0,"creation_date":1683922807,"post_id":76239380,"comment_id":134446462,"content_license":"CC BY-SA 4.0"},{"owner":{"account_id":16391519,"reputation":312,"user_id":11840155,"user_type":"registered","profile_image":"https://lh4.googleusercontent.com/-_Ah0_KXAULw/AAAAAAAAAAI/AAAAAAAAAEg/-fhh7DRVvv8/photo.jpg?sz=256","display_name":"Aoof","link":"https://stackoverflow.com/users/11840155/aoof"},"reply_to_user":{"account_id":3391382,"reputation":3116,"user_id":2846138,"user_type":"registered","profile_image":"https://i.stack.imgur.com/2sp68.png?s=256&g=1","display_name":"cyberbrain","link":"https://stackoverflow.com/users/2846138/cyberbrain"},"edited":false,"score":0,"creation_date":1683921427,"post_id":76239380,"comment_id":134446200,"content_license":"CC BY-SA 4.0"},{"owner":{"account_id":3391382,"reputation":3116,"user_id":2846138,"user_type":"registered","profile_image":"https://i.stack.imgur.com/2sp68.png?s=256&g=1","display_name":"cyberbrain","link":"https://stackoverflow.com/users/2846138/cyberbrain"},"edited":false,"score":1,"creation_date":1683920094,"post_id":76239380,"comment_id":134445984,"content_license":"CC BY-SA 4.0"},{"owner":{"account_id":2246079,"reputation":7956,"user_id":1979380,"user_type":"registered","accept_rate":89,"profile_image":"https://i.stack.imgur.com/3hHAd.jpg?s=256&g=1","display_name":"jarvo69","link":"https://stackoverflow.com/users/1979380/jarvo69"},"reply_to_user":{"account_id":6179310,"reputation":2524,"user_id":4815321,"user_type":"registered","profile_image":"https://www.gravatar.com/avatar/c7f1efe4e3c5d007dc7c5cc7d5a64e95?s=256&d=identicon&r=PG","display_name":"mr mcwolf","link":"https://stackoverflow.com/users/4815321/mr-mcwolf"},"edited":false,"score":0,"creation_date":1683346346,"post_id":76178871,"comment_id":134356695,"content_license":"CC BY-SA 4.0"},{"owner":{"account_id":6179310,"reputation":2524,"user_id":4815321,"user_type":"registered","profile_image":"https://www.gravatar.com/avatar/c7f1efe4e3c5d007dc7c5cc7d5a64e95?s=256&d=identicon&r=PG","display_name":"mr mcwolf","link":"https://stackoverflow.com/users/4815321/mr-mcwolf"},"edited":false,"score":0,"creation_date":1683266052,"post_id":76178871,"comment_id":134343257,"content_license":"CC BY-SA 4.0"}],"has_more":false,"quota_max":10000,"quota_remaining":9920}